higgsfield_client/__init__.py
higgsfield_client/auth.py
higgsfield_client/exceptions.py
higgsfield_client/http/__init__.py
higgsfield_client/http/client.py
higgsfield_client/http/error.py
higgsfield_client/http/retry.py
higgsfield_client/http/transport.py
higgsfield_client/mixins/__init__.py
higgsfield_client/mixins/upload.py
higgsfield_client/types_.py
higgsfield_client/utils.py
higgsfield_client-0.1.0.dist-info/METADATA
higgsfield_client-0.1.0.dist-info/WHEEL
higgsfield_client-0.1.0.dist-info/licenses/LICENSE
higgsfield_client-0.1.0.dist-info/RECORD
