Metadata-Version: 2.4
Name: higgsfield-client
Version: 0.1.0
Summary: Higgsfield API Python SDK
License-Expression: Apache-2.0
License-File: LICENSE
Author: Higgsfield
Author-email: support@higgsfield.ai
Requires-Python: >=3.8
Classifier: Programming Language :: Python :: 3
Classifier: Programming Language :: Python :: 3.8
Classifier: Programming Language :: Python :: 3.9
Classifier: Programming Language :: Python :: 3.10
Classifier: Programming Language :: Python :: 3.11
Classifier: Programming Language :: Python :: 3.12
Classifier: Programming Language :: Python :: 3.13
Classifier: Programming Language :: Python :: 3.14
Requires-Dist: httpx (>=0.21.0,<0.29.0)
Project-URL: Homepage, https://cloud.higgsfield.ai
Project-URL: Repository, https://github.com/higgsfield-ai/higgsfield-client
